odoo/addons/sale_commission_agent_restrict/README.rst
odoo/addons/sale_commission_agent_restrict/__init__.py
odoo/addons/sale_commission_agent_restrict/__manifest__.py
odoo/addons/sale_commission_agent_restrict/demo/res_users_demo.xml
odoo/addons/sale_commission_agent_restrict/i18n/es.po
odoo/addons/sale_commission_agent_restrict/i18n/it.po
odoo/addons/sale_commission_agent_restrict/i18n/pt_BR.po
odoo/addons/sale_commission_agent_restrict/i18n/sale_commission_agent_restrict.pot
odoo/addons/sale_commission_agent_restrict/models/__init__.py
odoo/addons/sale_commission_agent_restrict/models/res_partner.py
odoo/addons/sale_commission_agent_restrict/models/res_users.py
odoo/addons/sale_commission_agent_restrict/models/sale.py
odoo/addons/sale_commission_agent_restrict/models/sale_order_line.py
odoo/addons/sale_commission_agent_restrict/readme/CONFIGURE.rst
odoo/addons/sale_commission_agent_restrict/readme/CONTRIBUTORS.rst
odoo/addons/sale_commission_agent_restrict/readme/DESCRIPTION.rst
odoo/addons/sale_commission_agent_restrict/readme/USAGE.rst
odoo/addons/sale_commission_agent_restrict/security/ir.model.access.csv
odoo/addons/sale_commission_agent_restrict/security/security.xml
odoo/addons/sale_commission_agent_restrict/static/description/icon.png
odoo/addons/sale_commission_agent_restrict/static/description/icon.svg
odoo/addons/sale_commission_agent_restrict/static/description/index.html
odoo/addons/sale_commission_agent_restrict/tests/__init__.py
odoo/addons/sale_commission_agent_restrict/tests/test_sale_commission_agent_restrict.py
odoo/addons/sale_commission_agent_restrict/views/res_partner_views.xml
odoo/addons/sale_commission_agent_restrict/views/sale_order_view.xml
odoo_addon_sale_commission_agent_restrict-16.0.1.0.0.5.dist-info/METADATA
odoo_addon_sale_commission_agent_restrict-16.0.1.0.0.5.dist-info/WHEEL
odoo_addon_sale_commission_agent_restrict-16.0.1.0.0.5.dist-info/top_level.txt
odoo_addon_sale_commission_agent_restrict-16.0.1.0.0.5.dist-info/RECORD
