Metadata-Version: 2.1
Name: odoo-addon-sale_commission_agent_restrict
Version: 16.0.1.0.0.5
Summary: Sales Commissions Agent Restrict
Home-page: https://github.com/OCA/commission
Author: Ooops404, Ilyas, Odoo Community Association (OCA)
Author-email: support@odoo-community.org
License: AGPL-3
Classifier: Programming Language :: Python
Classifier: Framework :: Odoo
Classifier: Framework :: Odoo :: 16.0
Classifier: License :: OSI Approved :: GNU Affero General Public License v3
Requires-Python: >=3.10
Requires-Dist: odoo-addon-base-rule-visibility-restriction<16.1dev,>=16.0dev
Requires-Dist: odoo-addon-commission<16.1dev,>=16.0dev
Requires-Dist: odoo-addon-sale-commission<16.1dev,>=16.0dev
Requires-Dist: odoo<16.1dev,>=16.0a
